calcatime.py
calcatime-0.5.dist-info/entry_points.txt
calcatime-0.5.dist-info/LICENSE
calcatime-0.5.dist-info/WHEEL
calcatime-0.5.dist-info/METADATA
calcatime-0.5.dist-info/RECORD
