Metadata-Version: 2.1
Name: calcatime
Version: 0.5
Summary: Calculates total time from calendar events, grouped by an event attribute.
Home-page: https://github.com/eirannejad/calcatime
License: UNKNOWN
Author: Ehsan Iran-Nejad
Author-email: eirannejad@gmail.com
Classifier: License :: OSI Approved :: MIT License
Requires-Dist: docopt
Requires-Dist: exchangelib
